afm_learn/MakeVideo.py
afm_learn/__init__.py
afm_learn/afm_image_analyzer.py
afm_learn/afm_utils.py
afm_learn/afm_viz.py
afm_learn/cmap.py
afm_learn/domain_analysis.py
afm_learn/drawing_3d.py
afm_learn/skeleton.py
AFM_Learn-0.10.0.dist-info/LICENSE.txt
AFM_Learn-0.10.0.dist-info/METADATA
AFM_Learn-0.10.0.dist-info/WHEEL
AFM_Learn-0.10.0.dist-info/top_level.txt
AFM_Learn-0.10.0.dist-info/RECORD
