Metadata-Version: 2.2
Name: AFM-Learn
Version: 0.10.0
Summary: A Python package for visualizing and analyzing Atomic Force Microscopy(AFM) and Piezoelectric Force Microscopy(PFM) experimental data, offering tools to process, visualize, and extract meaningful insights from AFM images and measurements.
Home-page: https://github.com/pyscaffold/pyscaffold/
Author: Joshua C. Agar, Yichen Guo
Author-email: jca92@drexel.edu, yig319@lehigh.edu
License: MIT
Project-URL: Documentation, https://pyscaffold.org/
Platform: any
Classifier: Development Status :: 4 - Beta
Classifier: Programming Language :: Python
License-File: LICENSE.txt
Requires-Dist: numpy>=1.21.0
Requires-Dist: matplotlib>=3.5.0
Requires-Dist: scipy>=1.7.0
Requires-Dist: pandas>=1.3.0
Requires-Dist: xrayutilities
Requires-Dist: igor>=0.3
Requires-Dist: imutils
Requires-Dist: opencv-python
Requires-Dist: plotly>=5.0.0
Requires-Dist: seaborn
Provides-Extra: testing
Requires-Dist: setuptools; extra == "testing"
Requires-Dist: pytest; extra == "testing"
Requires-Dist: pytest-cov; extra == "testing"
